{
  "aspectWidth": 16,
  "aspectHeight": 9,
  "enableKeyboardZoom": false,
  "enableKeyboardRotation": false,
  "enableKeyboardNavigation": true,
  "enableMouseTranslation": false,
  "enableMouseZoom": false,
  "enableMouseRotation": false,
  "enableMouseNavigation": false,
  "updateURLOnFrameChange": true,
  "frames": [
    {
      "frameId": "f01",
      "title": "New frame",
      "titleLevel": 0,
      "notes": "",
      "timeoutMs": 3000,
      "timeoutEnable": true,
      "transitionDurationMs": 1000,
      "showInFrameList": false,
      "showFrameNumber": false,
      "layerProperties": {
        "layer2": {
          "link": false,
          "referenceElementId": "rect42675",
          "outlineElementId": "rect4477",
          "transitionTimingFunction": "linear",
          "transitionRelativeZoom": 0,
          "transitionPathId": ""
        },
        "layer1": {
          "link": false,
          "referenceElementId": "rect4477",
          "outlineElementId": "rect4477",
          "transitionTimingFunction": "linear",
          "transitionRelativeZoom": 0,
          "transitionPathId": ""
        },
        "__sozi_auto__": {
          "link": false,
          "referenceElementId": "",
          "outlineElementId": "rect4477",
          "transitionTimingFunction": "linear",
          "transitionRelativeZoom": 0,
          "transitionPathId": ""
        }
      },
      "cameraStates": {
        "layer2": {
          "cx": 154.61012268066406,
          "cy": 97.77778625488281,
          "width": 160,
          "height": 90,
          "opacity": 1,
          "angle": 0,
          "clipped": false,
          "clipXOffset": 0,
          "clipYOffset": 0,
          "clipWidthFactor": 1,
          "clipHeightFactor": 1
        },
        "layer1": {
          "cx": 154.61012268066406,
          "cy": 97.77778625488281,
          "width": 160,
          "height": 90,
          "opacity": 1,
          "angle": 0,
          "clipped": false,
          "clipXOffset": 0,
          "clipYOffset": 0,
          "clipWidthFactor": 1,
          "clipHeightFactor": 1
        },
        "__sozi_auto__": {
          "cx": 154.61012268066406,
          "cy": 97.77778625488281,
          "width": 160,
          "height": 90,
          "opacity": 1,
          "angle": 0,
          "clipped": false,
          "clipXOffset": 0,
          "clipYOffset": 0,
          "clipWidthFactor": 1,
          "clipHeightFactor": 1
        }
      },
      "cameraOffsets": {
        "layer2": {
          "deltaX": -502.64524841308594,
          "deltaY": -342.70445251464844,
          "widthFactor": 0.09980239321070829,
          "heightFactor": 0.08003453747347353,
          "deltaAngle": 0
        },
        "layer1": {
          "deltaX": 0,
          "deltaY": 0,
          "widthFactor": 1,
          "heightFactor": 1,
          "deltaAngle": 0
        }
      }
    },
    {
      "frameId": "f02",
      "title": "New frame",
      "titleLevel": 0,
      "notes": "",
      "timeoutMs": 0,
      "timeoutEnable": false,
      "transitionDurationMs": 1000,
      "showInFrameList": false,
      "showFrameNumber": false,
      "layerProperties": {
        "layer2": {
          "link": false,
          "referenceElementId": "rect42675",
          "outlineElementId": "rect863",
          "transitionTimingFunction": "linear",
          "transitionRelativeZoom": 0,
          "transitionPathId": ""
        },
        "layer1": {
          "link": false,
          "referenceElementId": "rect927",
          "outlineElementId": "rect863",
          "transitionTimingFunction": "linear",
          "transitionRelativeZoom": 0,
          "transitionPathId": ""
        },
        "__sozi_auto__": {
          "link": false,
          "referenceElementId": "",
          "outlineElementId": "rect863",
          "transitionTimingFunction": "linear",
          "transitionRelativeZoom": 0,
          "transitionPathId": ""
        }
      },
      "cameraStates": {
        "layer2": {
          "cx": 157.45944213867188,
          "cy": 231.9713134765625,
          "width": 160,
          "height": 90,
          "opacity": 1,
          "angle": 0,
          "clipped": false,
          "clipXOffset": 0,
          "clipYOffset": 0,
          "clipWidthFactor": 1,
          "clipHeightFactor": 1
        },
        "layer1": {
          "cx": 157.45944213867188,
          "cy": 231.9713134765625,
          "width": 160,
          "height": 90,
          "opacity": 1,
          "angle": 0,
          "clipped": false,
          "clipXOffset": 0,
          "clipYOffset": 0,
          "clipWidthFactor": 1,
          "clipHeightFactor": 1
        },
        "__sozi_auto__": {
          "cx": 157.45944213867188,
          "cy": 231.9713134765625,
          "width": 160,
          "height": 90,
          "opacity": 1,
          "angle": 0,
          "clipped": false,
          "clipXOffset": 0,
          "clipYOffset": 0,
          "clipWidthFactor": 1,
          "clipHeightFactor": 1
        }
      },
      "cameraOffsets": {
        "layer2": {
          "deltaX": -499.7959289550781,
          "deltaY": -208.51092529296875,
          "widthFactor": 0.09980239321070829,
          "heightFactor": 0.08003453747347353,
          "deltaAngle": 0
        },
        "layer1": {
          "deltaX": -201.00897216796875,
          "deltaY": -1.6053009033203125,
          "widthFactor": 1,
          "heightFactor": 1,
          "deltaAngle": 0
        }
      }
    },
    {
      "frameId": "f03",
      "title": "New frame",
      "titleLevel": 0,
      "notes": "",
      "timeoutMs": 0,
      "timeoutEnable": false,
      "transitionDurationMs": 1000,
      "showInFrameList": false,
      "showFrameNumber": false,
      "layerProperties": {
        "layer2": {
          "link": false,
          "referenceElementId": "rect42675",
          "outlineElementId": "rect927",
          "transitionTimingFunction": "linear",
          "transitionRelativeZoom": 0,
          "transitionPathId": ""
        },
        "layer1": {
          "link": false,
          "referenceElementId": "rect927-3",
          "outlineElementId": "rect927",
          "transitionTimingFunction": "linear",
          "transitionRelativeZoom": 0,
          "transitionPathId": ""
        },
        "__sozi_auto__": {
          "link": false,
          "referenceElementId": "",
          "outlineElementId": "rect927",
          "transitionTimingFunction": "linear",
          "transitionRelativeZoom": 0,
          "transitionPathId": ""
        }
      },
      "cameraStates": {
        "layer2": {
          "cx": 358.4684143066406,
          "cy": 233.5766143798828,
          "width": 160,
          "height": 90,
          "opacity": 1,
          "angle": 0,
          "clipped": false,
          "clipXOffset": 0,
          "clipYOffset": 0,
          "clipWidthFactor": 1,
          "clipHeightFactor": 1
        },
        "layer1": {
          "cx": 358.4684143066406,
          "cy": 233.5766143798828,
          "width": 160,
          "height": 90,
          "opacity": 1,
          "angle": 0,
          "clipped": false,
          "clipXOffset": 0,
          "clipYOffset": 0,
          "clipWidthFactor": 1,
          "clipHeightFactor": 1
        },
        "__sozi_auto__": {
          "cx": 358.4684143066406,
          "cy": 233.5766143798828,
          "width": 160,
          "height": 90,
          "opacity": 1,
          "angle": 0,
          "clipped": false,
          "clipXOffset": 0,
          "clipYOffset": 0,
          "clipWidthFactor": 1,
          "clipHeightFactor": 1
        }
      },
      "cameraOffsets": {
        "layer2": {
          "deltaX": -298.7869567871094,
          "deltaY": -206.90562438964844,
          "widthFactor": 0.09980239321070829,
          "heightFactor": 0.08003453747347353,
          "deltaAngle": 0
        },
        "layer1": {
          "deltaX": -386.5530090332031,
          "deltaY": -1.0448455810546875,
          "widthFactor": 1,
          "heightFactor": 1,
          "deltaAngle": 0
        }
      }
    },
    {
      "frameId": "f04",
      "title": "New frame",
      "titleLevel": 0,
      "notes": "",
      "timeoutMs": 0,
      "timeoutEnable": false,
      "transitionDurationMs": 1000,
      "showInFrameList": false,
      "showFrameNumber": false,
      "layerProperties": {
        "layer2": {
          "link": false,
          "referenceElementId": "rect42675",
          "outlineElementId": "rect16033",
          "transitionTimingFunction": "linear",
          "transitionRelativeZoom": 0,
          "transitionPathId": ""
        },
        "layer1": {
          "link": false,
          "referenceElementId": "rect16033",
          "outlineElementId": "rect16033",
          "transitionTimingFunction": "linear",
          "transitionRelativeZoom": 0,
          "transitionPathId": ""
        },
        "__sozi_auto__": {
          "link": false,
          "referenceElementId": "",
          "outlineElementId": "rect16033",
          "transitionTimingFunction": "linear",
          "transitionRelativeZoom": 0,
          "transitionPathId": ""
        }
      },
      "cameraStates": {
        "layer2": {
          "cx": 551.944091796875,
          "cy": 234.12454223632812,
          "width": 160,
          "height": 90,
          "opacity": 1,
          "angle": 0,
          "clipped": false,
          "clipXOffset": 0,
          "clipYOffset": 0,
          "clipWidthFactor": 1,
          "clipHeightFactor": 1
        },
        "layer1": {
          "cx": 551.944091796875,
          "cy": 234.12454223632812,
          "width": 160,
          "height": 90,
          "opacity": 1,
          "angle": 0,
          "clipped": false,
          "clipXOffset": 0,
          "clipYOffset": 0,
          "clipWidthFactor": 1,
          "clipHeightFactor": 1
        },
        "__sozi_auto__": {
          "cx": 551.944091796875,
          "cy": 234.12454223632812,
          "width": 160,
          "height": 90,
          "opacity": 1,
          "angle": 0,
          "clipped": false,
          "clipXOffset": 0,
          "clipYOffset": 0,
          "clipWidthFactor": 1,
          "clipHeightFactor": 1
        }
      },
      "cameraOffsets": {
        "layer2": {
          "deltaX": -105.311279296875,
          "deltaY": -206.35769653320312,
          "widthFactor": 0.09980239321070829,
          "heightFactor": 0.08003453747347353,
          "deltaAngle": 0
        },
        "layer1": {
          "deltaX": 0,
          "deltaY": 0,
          "widthFactor": 1,
          "heightFactor": 1,
          "deltaAngle": 0
        }
      }
    },
    {
      "frameId": "f05",
      "title": "New frame",
      "titleLevel": 0,
      "notes": "",
      "timeoutMs": 0,
      "timeoutEnable": false,
      "transitionDurationMs": 1000,
      "showInFrameList": false,
      "showFrameNumber": false,
      "layerProperties": {
        "layer2": {
          "link": false,
          "referenceElementId": "rect42675",
          "outlineElementId": "rect927-3",
          "transitionTimingFunction": "linear",
          "transitionRelativeZoom": 0,
          "transitionPathId": ""
        },
        "layer1": {
          "link": false,
          "referenceElementId": "rect927-3",
          "outlineElementId": "rect927-3",
          "transitionTimingFunction": "linear",
          "transitionRelativeZoom": 0,
          "transitionPathId": ""
        },
        "__sozi_auto__": {
          "link": false,
          "referenceElementId": "",
          "outlineElementId": "rect927-3",
          "transitionTimingFunction": "linear",
          "transitionRelativeZoom": 0,
          "transitionPathId": ""
        }
      },
      "cameraStates": {
        "layer2": {
          "cx": 745.0214233398438,
          "cy": 234.6214599609375,
          "width": 160,
          "height": 90,
          "opacity": 1,
          "angle": 0,
          "clipped": false,
          "clipXOffset": 0,
          "clipYOffset": 0,
          "clipWidthFactor": 1,
          "clipHeightFactor": 1
        },
        "layer1": {
          "cx": 745.0214233398438,
          "cy": 234.6214599609375,
          "width": 160,
          "height": 90,
          "opacity": 1,
          "angle": 0,
          "clipped": false,
          "clipXOffset": 0,
          "clipYOffset": 0,
          "clipWidthFactor": 1,
          "clipHeightFactor": 1
        },
        "__sozi_auto__": {
          "cx": 745.0214233398438,
          "cy": 234.6214599609375,
          "width": 160,
          "height": 90,
          "opacity": 1,
          "angle": 0,
          "clipped": false,
          "clipXOffset": 0,
          "clipYOffset": 0,
          "clipWidthFactor": 1,
          "clipHeightFactor": 1
        }
      },
      "cameraOffsets": {
        "layer2": {
          "deltaX": 87.76605224609375,
          "deltaY": -205.86077880859375,
          "widthFactor": 0.09980239321070829,
          "heightFactor": 0.08003453747347353,
          "deltaAngle": 0
        },
        "layer1": {
          "deltaX": 0,
          "deltaY": 0,
          "widthFactor": 1,
          "heightFactor": 1,
          "deltaAngle": 0
        }
      }
    },
    {
      "frameId": "f06",
      "title": "New frame",
      "titleLevel": 0,
      "notes": "",
      "timeoutMs": 0,
      "timeoutEnable": false,
      "transitionDurationMs": 1000,
      "showInFrameList": false,
      "showFrameNumber": false,
      "layerProperties": {
        "layer2": {
          "link": false,
          "referenceElementId": "rect42675",
          "outlineElementId": "rect50909",
          "transitionTimingFunction": "linear",
          "transitionRelativeZoom": 0,
          "transitionPathId": ""
        },
        "layer1": {
          "link": false,
          "referenceElementId": "rect50909",
          "outlineElementId": "rect50909",
          "transitionTimingFunction": "linear",
          "transitionRelativeZoom": 0,
          "transitionPathId": ""
        },
        "__sozi_auto__": {
          "link": false,
          "referenceElementId": "",
          "outlineElementId": "rect50909",
          "transitionTimingFunction": "linear",
          "transitionRelativeZoom": 0,
          "transitionPathId": ""
        }
      },
      "cameraStates": {
        "layer2": {
          "cx": 745.6661987304688,
          "cy": 354.2982177734375,
          "width": 160,
          "height": 90,
          "opacity": 1,
          "angle": 0,
          "clipped": false,
          "clipXOffset": 0,
          "clipYOffset": 0,
          "clipWidthFactor": 1,
          "clipHeightFactor": 1
        },
        "layer1": {
          "cx": 745.6661987304688,
          "cy": 354.2982177734375,
          "width": 160,
          "height": 90,
          "opacity": 1,
          "angle": 0,
          "clipped": false,
          "clipXOffset": 0,
          "clipYOffset": 0,
          "clipWidthFactor": 1,
          "clipHeightFactor": 1
        },
        "__sozi_auto__": {
          "cx": 745.6661987304688,
          "cy": 354.2982177734375,
          "width": 160,
          "height": 90,
          "opacity": 1,
          "angle": 0,
          "clipped": false,
          "clipXOffset": 0,
          "clipYOffset": 0,
          "clipWidthFactor": 1,
          "clipHeightFactor": 1
        }
      },
      "cameraOffsets": {
        "layer2": {
          "deltaX": 88.41082763671875,
          "deltaY": -86.18402099609375,
          "widthFactor": 0.09980239321070829,
          "heightFactor": 0.08003453747347353,
          "deltaAngle": 0
        },
        "layer1": {
          "deltaX": 0,
          "deltaY": 0,
          "widthFactor": 1,
          "heightFactor": 1,
          "deltaAngle": 0
        }
      }
    },
    {
      "frameId": "f07",
      "title": "New frame",
      "titleLevel": 0,
      "notes": "",
      "timeoutMs": 0,
      "timeoutEnable": false,
      "transitionDurationMs": 1000,
      "showInFrameList": false,
      "showFrameNumber": false,
      "layerProperties": {
        "layer2": {
          "link": false,
          "referenceElementId": "rect42675",
          "outlineElementId": "rect7150",
          "transitionTimingFunction": "linear",
          "transitionRelativeZoom": 0,
          "transitionPathId": ""
        },
        "layer1": {
          "link": false,
          "referenceElementId": "rect7150",
          "outlineElementId": "rect7150",
          "transitionTimingFunction": "linear",
          "transitionRelativeZoom": 0,
          "transitionPathId": ""
        },
        "__sozi_auto__": {
          "link": false,
          "referenceElementId": "",
          "outlineElementId": "rect7150",
          "transitionTimingFunction": "linear",
          "transitionRelativeZoom": 0,
          "transitionPathId": ""
        }
      },
      "cameraStates": {
        "layer2": {
          "cx": 934.587890625,
          "cy": 354.3475646972656,
          "width": 160,
          "height": 90,
          "opacity": 1,
          "angle": 0,
          "clipped": false,
          "clipXOffset": 0,
          "clipYOffset": 0,
          "clipWidthFactor": 1,
          "clipHeightFactor": 1
        },
        "layer1": {
          "cx": 934.587890625,
          "cy": 354.3475646972656,
          "width": 160,
          "height": 90,
          "opacity": 1,
          "angle": 0,
          "clipped": false,
          "clipXOffset": 0,
          "clipYOffset": 0,
          "clipWidthFactor": 1,
          "clipHeightFactor": 1
        },
        "__sozi_auto__": {
          "cx": 934.587890625,
          "cy": 354.3475646972656,
          "width": 160,
          "height": 90,
          "opacity": 1,
          "angle": 0,
          "clipped": false,
          "clipXOffset": 0,
          "clipYOffset": 0,
          "clipWidthFactor": 1,
          "clipHeightFactor": 1
        }
      },
      "cameraOffsets": {
        "layer2": {
          "deltaX": 277.33251953125,
          "deltaY": -86.13467407226562,
          "widthFactor": 0.09980239321070829,
          "heightFactor": 0.08003453747347353,
          "deltaAngle": 0
        },
        "layer1": {
          "deltaX": 0,
          "deltaY": 0,
          "widthFactor": 1,
          "heightFactor": 1,
          "deltaAngle": 0
        }
      }
    },
    {
      "frameId": "f08",
      "title": "New frame",
      "titleLevel": 0,
      "notes": "",
      "timeoutMs": 0,
      "timeoutEnable": false,
      "transitionDurationMs": 1000,
      "showInFrameList": false,
      "showFrameNumber": false,
      "layerProperties": {
        "layer2": {
          "link": false,
          "referenceElementId": "rect42675",
          "outlineElementId": "rect7704",
          "transitionTimingFunction": "linear",
          "transitionRelativeZoom": 0,
          "transitionPathId": ""
        },
        "layer1": {
          "link": false,
          "referenceElementId": "rect7704",
          "outlineElementId": "rect7704",
          "transitionTimingFunction": "linear",
          "transitionRelativeZoom": 0,
          "transitionPathId": ""
        },
        "__sozi_auto__": {
          "link": false,
          "referenceElementId": "",
          "outlineElementId": "rect7704",
          "transitionTimingFunction": "linear",
          "transitionRelativeZoom": 0,
          "transitionPathId": ""
        }
      },
      "cameraStates": {
        "layer2": {
          "cx": 1120.9793701171875,
          "cy": 351.96881103515625,
          "width": 160,
          "height": 90,
          "opacity": 1,
          "angle": 0,
          "clipped": false,
          "clipXOffset": 0,
          "clipYOffset": 0,
          "clipWidthFactor": 1,
          "clipHeightFactor": 1
        },
        "layer1": {
          "cx": 1120.9793701171875,
          "cy": 351.96881103515625,
          "width": 160,
          "height": 90,
          "opacity": 1,
          "angle": 0,
          "clipped": false,
          "clipXOffset": 0,
          "clipYOffset": 0,
          "clipWidthFactor": 1,
          "clipHeightFactor": 1
        },
        "__sozi_auto__": {
          "cx": 1120.9793701171875,
          "cy": 351.96881103515625,
          "width": 160,
          "height": 90,
          "opacity": 1,
          "angle": 0,
          "clipped": false,
          "clipXOffset": 0,
          "clipYOffset": 0,
          "clipWidthFactor": 1,
          "clipHeightFactor": 1
        }
      },
      "cameraOffsets": {
        "layer2": {
          "deltaX": 463.7239990234375,
          "deltaY": -88.513427734375,
          "widthFactor": 0.09980239321070829,
          "heightFactor": 0.08003453747347353,
          "deltaAngle": 0
        },
        "layer1": {
          "deltaX": 0,
          "deltaY": 0,
          "widthFactor": 1,
          "heightFactor": 1,
          "deltaAngle": 0
        }
      }
    },
    {
      "frameId": "f09",
      "title": "New frame",
      "titleLevel": 0,
      "notes": "",
      "timeoutMs": 0,
      "timeoutEnable": false,
      "transitionDurationMs": 1000,
      "showInFrameList": false,
      "showFrameNumber": false,
      "layerProperties": {
        "layer2": {
          "link": false,
          "referenceElementId": "rect42675",
          "outlineElementId": "rect7729",
          "transitionTimingFunction": "linear",
          "transitionRelativeZoom": 0,
          "transitionPathId": ""
        },
        "layer1": {
          "link": false,
          "referenceElementId": "rect7729",
          "outlineElementId": "rect7729",
          "transitionTimingFunction": "linear",
          "transitionRelativeZoom": 0,
          "transitionPathId": ""
        },
        "__sozi_auto__": {
          "link": false,
          "referenceElementId": "",
          "outlineElementId": "rect7729",
          "transitionTimingFunction": "linear",
          "transitionRelativeZoom": 0,
          "transitionPathId": ""
        }
      },
      "cameraStates": {
        "layer2": {
          "cx": 1300.0296630859375,
          "cy": 351.96881103515625,
          "width": 160,
          "height": 90,
          "opacity": 1,
          "angle": 0,
          "clipped": false,
          "clipXOffset": 0,
          "clipYOffset": 0,
          "clipWidthFactor": 1,
          "clipHeightFactor": 1
        },
        "layer1": {
          "cx": 1300.0296630859375,
          "cy": 351.96881103515625,
          "width": 160,
          "height": 90,
          "opacity": 1,
          "angle": 0,
          "clipped": false,
          "clipXOffset": 0,
          "clipYOffset": 0,
          "clipWidthFactor": 1,
          "clipHeightFactor": 1
        },
        "__sozi_auto__": {
          "cx": 1300.0296630859375,
          "cy": 351.96881103515625,
          "width": 160,
          "height": 90,
          "opacity": 1,
          "angle": 0,
          "clipped": false,
          "clipXOffset": 0,
          "clipYOffset": 0,
          "clipWidthFactor": 1,
          "clipHeightFactor": 1
        }
      },
      "cameraOffsets": {
        "layer2": {
          "deltaX": 642.7742919921875,
          "deltaY": -88.513427734375,
          "widthFactor": 0.09980239321070829,
          "heightFactor": 0.08003453747347353,
          "deltaAngle": 0
        },
        "layer1": {
          "deltaX": 0,
          "deltaY": 0,
          "widthFactor": 1,
          "heightFactor": 1,
          "deltaAngle": 0
        }
      }
    },
    {
      "frameId": "f10",
      "title": "New frame",
      "titleLevel": 0,
      "notes": "",
      "timeoutMs": 0,
      "timeoutEnable": false,
      "transitionDurationMs": 1000,
      "showInFrameList": false,
      "showFrameNumber": false,
      "layerProperties": {
        "layer2": {
          "link": false,
          "referenceElementId": "rect42675",
          "outlineElementId": "rect27155",
          "transitionTimingFunction": "linear",
          "transitionRelativeZoom": 0,
          "transitionPathId": ""
        },
        "layer1": {
          "link": false,
          "referenceElementId": "rect57342",
          "outlineElementId": "rect27155",
          "transitionTimingFunction": "linear",
          "transitionRelativeZoom": 0,
          "transitionPathId": ""
        },
        "__sozi_auto__": {
          "link": false,
          "referenceElementId": "",
          "outlineElementId": "rect27155",
          "transitionTimingFunction": "linear",
          "transitionRelativeZoom": 0,
          "transitionPathId": ""
        }
      },
      "cameraStates": {
        "layer2": {
          "cx": 1301.92138671875,
          "cy": 479.3307189941406,
          "width": 160,
          "height": 90,
          "opacity": 1,
          "angle": 0,
          "clipped": false,
          "clipXOffset": 0,
          "clipYOffset": 0,
          "clipWidthFactor": 1,
          "clipHeightFactor": 1
        },
        "layer1": {
          "cx": 1301.92138671875,
          "cy": 479.3307189941406,
          "width": 160,
          "height": 90,
          "opacity": 1,
          "angle": 0,
          "clipped": false,
          "clipXOffset": 0,
          "clipYOffset": 0,
          "clipWidthFactor": 1,
          "clipHeightFactor": 1
        },
        "__sozi_auto__": {
          "cx": 1301.92138671875,
          "cy": 479.3307189941406,
          "width": 160,
          "height": 90,
          "opacity": 1,
          "angle": 0,
          "clipped": false,
          "clipXOffset": 0,
          "clipYOffset": 0,
          "clipWidthFactor": 1,
          "clipHeightFactor": 1
        }
      },
      "cameraOffsets": {
        "layer2": {
          "deltaX": 644.666015625,
          "deltaY": 38.848480224609375,
          "widthFactor": 0.09980239321070829,
          "heightFactor": 0.08003453747347353,
          "deltaAngle": 0
        },
        "layer1": {
          "deltaX": 366.6175537109375,
          "deltaY": -0.449981689453125,
          "widthFactor": 1.3333333333333333,
          "heightFactor": 1,
          "deltaAngle": 0
        }
      }
    },
    {
      "frameId": "f11",
      "title": "New frame",
      "titleLevel": 0,
      "notes": "",
      "timeoutMs": 0,
      "timeoutEnable": false,
      "transitionDurationMs": 1000,
      "showInFrameList": false,
      "showFrameNumber": false,
      "layerProperties": {
        "layer2": {
          "link": false,
          "referenceElementId": "rect42675",
          "outlineElementId": "rect30600",
          "transitionTimingFunction": "linear",
          "transitionRelativeZoom": 0,
          "transitionPathId": ""
        },
        "layer1": {
          "link": false,
          "referenceElementId": "rect23701",
          "outlineElementId": "rect30600",
          "transitionTimingFunction": "linear",
          "transitionRelativeZoom": 0,
          "transitionPathId": ""
        },
        "__sozi_auto__": {
          "link": false,
          "referenceElementId": "",
          "outlineElementId": "rect30600",
          "transitionTimingFunction": "linear",
          "transitionRelativeZoom": 0,
          "transitionPathId": ""
        }
      },
      "cameraStates": {
        "layer2": {
          "cx": 1119.696044921875,
          "cy": 479.8598937988281,
          "width": 160,
          "height": 90,
          "opacity": 1,
          "angle": 0,
          "clipped": false,
          "clipXOffset": 0,
          "clipYOffset": 0,
          "clipWidthFactor": 1,
          "clipHeightFactor": 1
        },
        "layer1": {
          "cx": 1119.696044921875,
          "cy": 479.8598937988281,
          "width": 160,
          "height": 90,
          "opacity": 1,
          "angle": 0,
          "clipped": false,
          "clipXOffset": 0,
          "clipYOffset": 0,
          "clipWidthFactor": 1,
          "clipHeightFactor": 1
        },
        "__sozi_auto__": {
          "cx": 1119.696044921875,
          "cy": 479.8598937988281,
          "width": 160,
          "height": 90,
          "opacity": 1,
          "angle": 0,
          "clipped": false,
          "clipXOffset": 0,
          "clipYOffset": 0,
          "clipWidthFactor": 1,
          "clipHeightFactor": 1
        }
      },
      "cameraOffsets": {
        "layer2": {
          "deltaX": 462.440673828125,
          "deltaY": 39.377655029296875,
          "widthFactor": 0.09980239321070829,
          "heightFactor": 0.08003453747347353,
          "deltaAngle": 0
        },
        "layer1": {
          "deltaX": 184.3922119140625,
          "deltaY": 0.079071044921875,
          "widthFactor": 1,
          "heightFactor": 1,
          "deltaAngle": 0
        }
      }
    },
    {
      "frameId": "f12",
      "title": "New frame",
      "titleLevel": 0,
      "notes": "",
      "timeoutMs": 0,
      "timeoutEnable": false,
      "transitionDurationMs": 1000,
      "showInFrameList": false,
      "showFrameNumber": false,
      "layerProperties": {
        "layer2": {
          "link": false,
          "referenceElementId": "rect42675",
          "outlineElementId": "rect23701",
          "transitionTimingFunction": "linear",
          "transitionRelativeZoom": 0,
          "transitionPathId": ""
        },
        "layer1": {
          "link": false,
          "referenceElementId": "rect23701",
          "outlineElementId": "rect23701",
          "transitionTimingFunction": "linear",
          "transitionRelativeZoom": 0,
          "transitionPathId": ""
        },
        "__sozi_auto__": {
          "link": false,
          "referenceElementId": "",
          "outlineElementId": "rect23701",
          "transitionTimingFunction": "linear",
          "transitionRelativeZoom": 0,
          "transitionPathId": ""
        }
      },
      "cameraStates": {
        "layer2": {
          "cx": 935.3038330078125,
          "cy": 479.78082275390625,
          "width": 160,
          "height": 90,
          "opacity": 1,
          "angle": 0,
          "clipped": false,
          "clipXOffset": 0,
          "clipYOffset": 0,
          "clipWidthFactor": 1,
          "clipHeightFactor": 1
        },
        "layer1": {
          "cx": 935.3038330078125,
          "cy": 479.78082275390625,
          "width": 160,
          "height": 90,
          "opacity": 1,
          "angle": 0,
          "clipped": false,
          "clipXOffset": 0,
          "clipYOffset": 0,
          "clipWidthFactor": 1,
          "clipHeightFactor": 1
        },
        "__sozi_auto__": {
          "cx": 935.3038330078125,
          "cy": 479.78082275390625,
          "width": 160,
          "height": 90,
          "opacity": 1,
          "angle": 0,
          "clipped": false,
          "clipXOffset": 0,
          "clipYOffset": 0,
          "clipWidthFactor": 1,
          "clipHeightFactor": 1
        }
      },
      "cameraOffsets": {
        "layer2": {
          "deltaX": 278.0484619140625,
          "deltaY": 39.298583984375,
          "widthFactor": 0.09980239321070829,
          "heightFactor": 0.08003453747347353,
          "deltaAngle": 0
        },
        "layer1": {
          "deltaX": 0,
          "deltaY": 0,
          "widthFactor": 1,
          "heightFactor": 1,
          "deltaAngle": 0
        }
      }
    },
    {
      "frameId": "f13",
      "title": "New frame",
      "titleLevel": 0,
      "notes": "",
      "timeoutMs": 0,
      "timeoutEnable": false,
      "transitionDurationMs": 1000,
      "showInFrameList": false,
      "showFrameNumber": false,
      "layerProperties": {
        "layer2": {
          "link": false,
          "referenceElementId": "rect42675",
          "outlineElementId": "rect27153",
          "transitionTimingFunction": "linear",
          "transitionRelativeZoom": 0,
          "transitionPathId": ""
        },
        "layer1": {
          "link": false,
          "referenceElementId": "rect30874",
          "outlineElementId": "rect27153",
          "transitionTimingFunction": "linear",
          "transitionRelativeZoom": 0,
          "transitionPathId": ""
        },
        "__sozi_auto__": {
          "link": false,
          "referenceElementId": "",
          "outlineElementId": "rect27153",
          "transitionTimingFunction": "linear",
          "transitionRelativeZoom": 0,
          "transitionPathId": ""
        }
      },
      "cameraStates": {
        "layer2": {
          "cx": 752.5928955078125,
          "cy": 479.79681396484375,
          "width": 160,
          "height": 90,
          "opacity": 1,
          "angle": 0,
          "clipped": false,
          "clipXOffset": 0,
          "clipYOffset": 0,
          "clipWidthFactor": 1,
          "clipHeightFactor": 1
        },
        "layer1": {
          "cx": 752.5928955078125,
          "cy": 479.79681396484375,
          "width": 160,
          "height": 90,
          "opacity": 1,
          "angle": 0,
          "clipped": false,
          "clipXOffset": 0,
          "clipYOffset": 0,
          "clipWidthFactor": 1,
          "clipHeightFactor": 1
        },
        "__sozi_auto__": {
          "cx": 752.5928955078125,
          "cy": 479.79681396484375,
          "width": 160,
          "height": 90,
          "opacity": 1,
          "angle": 0,
          "clipped": false,
          "clipXOffset": 0,
          "clipYOffset": 0,
          "clipWidthFactor": 1,
          "clipHeightFactor": 1
        }
      },
      "cameraOffsets": {
        "layer2": {
          "deltaX": 95.3375244140625,
          "deltaY": 39.3145751953125,
          "widthFactor": 0.09980239321070829,
          "heightFactor": 0.08003453747347353,
          "deltaAngle": 0
        },
        "layer1": {
          "deltaX": 189.718017578125,
          "deltaY": -0.536376953125,
          "widthFactor": 1,
          "heightFactor": 1,
          "deltaAngle": 0
        }
      }
    },
    {
      "frameId": "f14",
      "title": "New frame",
      "titleLevel": 0,
      "notes": "",
      "timeoutMs": 0,
      "timeoutEnable": false,
      "transitionDurationMs": 1000,
      "showInFrameList": false,
      "showFrameNumber": false,
      "layerProperties": {
        "layer2": {
          "link": false,
          "referenceElementId": "rect42675",
          "outlineElementId": "rect30874",
          "transitionTimingFunction": "linear",
          "transitionRelativeZoom": 0,
          "transitionPathId": ""
        },
        "layer1": {
          "link": false,
          "referenceElementId": "rect53782",
          "outlineElementId": "rect30874",
          "transitionTimingFunction": "linear",
          "transitionRelativeZoom": 0,
          "transitionPathId": ""
        },
        "__sozi_auto__": {
          "link": false,
          "referenceElementId": "",
          "outlineElementId": "rect30874",
          "transitionTimingFunction": "linear",
          "transitionRelativeZoom": 0,
          "transitionPathId": ""
        }
      },
      "cameraStates": {
        "layer2": {
          "cx": 562.8748779296875,
          "cy": 480.33319091796875,
          "width": 160,
          "height": 90,
          "opacity": 1,
          "angle": 0,
          "clipped": false,
          "clipXOffset": 0,
          "clipYOffset": 0,
          "clipWidthFactor": 1,
          "clipHeightFactor": 1
        },
        "layer1": {
          "cx": 562.8748779296875,
          "cy": 480.33319091796875,
          "width": 160,
          "height": 90,
          "opacity": 1,
          "angle": 0,
          "clipped": false,
          "clipXOffset": 0,
          "clipYOffset": 0,
          "clipWidthFactor": 1,
          "clipHeightFactor": 1
        },
        "__sozi_auto__": {
          "cx": 562.8748779296875,
          "cy": 480.33319091796875,
          "width": 160,
          "height": 90,
          "opacity": 1,
          "angle": 0,
          "clipped": false,
          "clipXOffset": 0,
          "clipYOffset": 0,
          "clipWidthFactor": 1,
          "clipHeightFactor": 1
        }
      },
      "cameraOffsets": {
        "layer2": {
          "deltaX": -94.3804931640625,
          "deltaY": 39.8509521484375,
          "widthFactor": 0.09980239321070829,
          "heightFactor": 0.08003453747347353,
          "deltaAngle": 0
        },
        "layer1": {
          "deltaX": 194.11843872070312,
          "deltaY": 2.148895263671875,
          "widthFactor": 1,
          "heightFactor": 1,
          "deltaAngle": 0
        }
      }
    },
    {
      "frameId": "f15",
      "title": "New frame",
      "titleLevel": 0,
      "notes": "",
      "timeoutMs": 0,
      "timeoutEnable": false,
      "transitionDurationMs": 1000,
      "showInFrameList": false,
      "showFrameNumber": false,
      "layerProperties": {
        "layer2": {
          "link": false,
          "referenceElementId": "rect42675",
          "outlineElementId": "rect53782",
          "transitionTimingFunction": "linear",
          "transitionRelativeZoom": 0,
          "transitionPathId": ""
        },
        "layer1": {
          "link": false,
          "referenceElementId": "rect28674",
          "outlineElementId": "rect53782",
          "transitionTimingFunction": "linear",
          "transitionRelativeZoom": 0,
          "transitionPathId": ""
        },
        "__sozi_auto__": {
          "link": false,
          "referenceElementId": "",
          "outlineElementId": "rect53782",
          "transitionTimingFunction": "linear",
          "transitionRelativeZoom": 0,
          "transitionPathId": ""
        }
      },
      "cameraStates": {
        "layer2": {
          "cx": 368.7564392089844,
          "cy": 478.1842956542969,
          "width": 160,
          "height": 90,
          "opacity": 1,
          "angle": 0,
          "clipped": false,
          "clipXOffset": 0,
          "clipYOffset": 0,
          "clipWidthFactor": 1,
          "clipHeightFactor": 1
        },
        "layer1": {
          "cx": 368.7564392089844,
          "cy": 478.1842956542969,
          "width": 160,
          "height": 90,
          "opacity": 1,
          "angle": 0,
          "clipped": false,
          "clipXOffset": 0,
          "clipYOffset": 0,
          "clipWidthFactor": 1,
          "clipHeightFactor": 1
        },
        "__sozi_auto__": {
          "cx": 368.7564392089844,
          "cy": 478.1842956542969,
          "width": 160,
          "height": 90,
          "opacity": 1,
          "angle": 0,
          "clipped": false,
          "clipXOffset": 0,
          "clipYOffset": 0,
          "clipWidthFactor": 1,
          "clipHeightFactor": 1
        }
      },
      "cameraOffsets": {
        "layer2": {
          "deltaX": -288.4989318847656,
          "deltaY": 37.702056884765625,
          "widthFactor": 0.09980239321070829,
          "heightFactor": 0.08003453747347353,
          "deltaAngle": 0
        },
        "layer1": {
          "deltaX": 0.144256591796875,
          "deltaY": -131.21127319335938,
          "widthFactor": 1,
          "heightFactor": 1,
          "deltaAngle": 0
        }
      }
    },
    {
      "frameId": "f16",
      "title": "New frame",
      "titleLevel": 0,
      "notes": "",
      "timeoutMs": 0,
      "timeoutEnable": false,
      "transitionDurationMs": 1000,
      "showInFrameList": false,
      "showFrameNumber": false,
      "layerProperties": {
        "layer2": {
          "link": false,
          "referenceElementId": "rect42675",
          "outlineElementId": "rect28674",
          "transitionTimingFunction": "linear",
          "transitionRelativeZoom": 0,
          "transitionPathId": ""
        },
        "layer1": {
          "link": false,
          "referenceElementId": "rect28900",
          "outlineElementId": "rect28674",
          "transitionTimingFunction": "linear",
          "transitionRelativeZoom": 0,
          "transitionPathId": ""
        },
        "__sozi_auto__": {
          "link": false,
          "referenceElementId": "",
          "outlineElementId": "rect28674",
          "transitionTimingFunction": "linear",
          "transitionRelativeZoom": 0,
          "transitionPathId": ""
        }
      },
      "cameraStates": {
        "layer2": {
          "cx": 368.6121826171875,
          "cy": 609.3955688476562,
          "width": 160,
          "height": 90,
          "opacity": 1,
          "angle": 0,
          "clipped": false,
          "clipXOffset": 0,
          "clipYOffset": 0,
          "clipWidthFactor": 1,
          "clipHeightFactor": 1
        },
        "layer1": {
          "cx": 368.6121826171875,
          "cy": 609.3955688476562,
          "width": 160,
          "height": 90,
          "opacity": 1,
          "angle": 0,
          "clipped": false,
          "clipXOffset": 0,
          "clipYOffset": 0,
          "clipWidthFactor": 1,
          "clipHeightFactor": 1
        },
        "__sozi_auto__": {
          "cx": 368.6121826171875,
          "cy": 609.3955688476562,
          "width": 160,
          "height": 90,
          "opacity": 1,
          "angle": 0,
          "clipped": false,
          "clipXOffset": 0,
          "clipYOffset": 0,
          "clipWidthFactor": 1,
          "clipHeightFactor": 1
        }
      },
      "cameraOffsets": {
        "layer2": {
          "deltaX": -288.6431884765625,
          "deltaY": 168.913330078125,
          "widthFactor": 0.09980239321070829,
          "heightFactor": 0.08003453747347353,
          "deltaAngle": 0
        },
        "layer1": {
          "deltaX": -195.59765625,
          "deltaY": 0.9755859375,
          "widthFactor": 1,
          "heightFactor": 1,
          "deltaAngle": 0
        }
      }
    },
    {
      "frameId": "f17",
      "title": "New frame",
      "titleLevel": 0,
      "notes": "",
      "timeoutMs": 0,
      "timeoutEnable": false,
      "transitionDurationMs": 1000,
      "showInFrameList": false,
      "showFrameNumber": false,
      "layerProperties": {
        "layer2": {
          "link": false,
          "referenceElementId": "rect42675",
          "outlineElementId": "rect28900",
          "transitionTimingFunction": "linear",
          "transitionRelativeZoom": 0,
          "transitionPathId": ""
        },
        "layer1": {
          "link": false,
          "referenceElementId": "rect28704",
          "outlineElementId": "rect28900",
          "transitionTimingFunction": "linear",
          "transitionRelativeZoom": 0,
          "transitionPathId": ""
        },
        "__sozi_auto__": {
          "link": false,
          "referenceElementId": "",
          "outlineElementId": "rect28900",
          "transitionTimingFunction": "linear",
          "transitionRelativeZoom": 0,
          "transitionPathId": ""
        }
      },
      "cameraStates": {
        "layer2": {
          "cx": 564.2098388671875,
          "cy": 608.4199829101562,
          "width": 160,
          "height": 90,
          "opacity": 1,
          "angle": 0,
          "clipped": false,
          "clipXOffset": 0,
          "clipYOffset": 0,
          "clipWidthFactor": 1,
          "clipHeightFactor": 1
        },
        "layer1": {
          "cx": 564.2098388671875,
          "cy": 608.4199829101562,
          "width": 160,
          "height": 90,
          "opacity": 1,
          "angle": 0,
          "clipped": false,
          "clipXOffset": 0,
          "clipYOffset": 0,
          "clipWidthFactor": 1,
          "clipHeightFactor": 1
        },
        "__sozi_auto__": {
          "cx": 564.2098388671875,
          "cy": 608.4199829101562,
          "width": 160,
          "height": 90,
          "opacity": 1,
          "angle": 0,
          "clipped": false,
          "clipXOffset": 0,
          "clipYOffset": 0,
          "clipWidthFactor": 1,
          "clipHeightFactor": 1
        }
      },
      "cameraOffsets": {
        "layer2": {
          "deltaX": -93.0455322265625,
          "deltaY": 167.937744140625,
          "widthFactor": 0.09980239321070829,
          "heightFactor": 0.08003453747347353,
          "deltaAngle": 0
        },
        "layer1": {
          "deltaX": -189.68609619140625,
          "deltaY": 0.56231689453125,
          "widthFactor": 1,
          "heightFactor": 1,
          "deltaAngle": 0
        }
      }
    },
    {
      "frameId": "f18",
      "title": "New frame",
      "titleLevel": 0,
      "notes": "",
      "timeoutMs": 0,
      "timeoutEnable": false,
      "transitionDurationMs": 1000,
      "showInFrameList": false,
      "showFrameNumber": false,
      "layerProperties": {
        "layer2": {
          "link": false,
          "referenceElementId": "rect42675",
          "outlineElementId": "rect28704",
          "transitionTimingFunction": "linear",
          "transitionRelativeZoom": 0,
          "transitionPathId": ""
        },
        "layer1": {
          "link": false,
          "referenceElementId": "rect7020",
          "outlineElementId": "rect28704",
          "transitionTimingFunction": "linear",
          "transitionRelativeZoom": 0,
          "transitionPathId": ""
        },
        "__sozi_auto__": {
          "link": false,
          "referenceElementId": "",
          "outlineElementId": "rect28704",
          "transitionTimingFunction": "linear",
          "transitionRelativeZoom": 0,
          "transitionPathId": ""
        }
      },
      "cameraStates": {
        "layer2": {
          "cx": 753.8959350585938,
          "cy": 607.857666015625,
          "width": 160,
          "height": 90,
          "opacity": 1,
          "angle": 0,
          "clipped": false,
          "clipXOffset": 0,
          "clipYOffset": 0,
          "clipWidthFactor": 1,
          "clipHeightFactor": 1
        },
        "layer1": {
          "cx": 753.8959350585938,
          "cy": 607.857666015625,
          "width": 160,
          "height": 90,
          "opacity": 1,
          "angle": 0,
          "clipped": false,
          "clipXOffset": 0,
          "clipYOffset": 0,
          "clipWidthFactor": 1,
          "clipHeightFactor": 1
        },
        "__sozi_auto__": {
          "cx": 753.8959350585938,
          "cy": 607.857666015625,
          "width": 160,
          "height": 90,
          "opacity": 1,
          "angle": 0,
          "clipped": false,
          "clipXOffset": 0,
          "clipYOffset": 0,
          "clipWidthFactor": 1,
          "clipHeightFactor": 1
        }
      },
      "cameraOffsets": {
        "layer2": {
          "deltaX": 96.64056396484375,
          "deltaY": 167.37542724609375,
          "widthFactor": 0.09980239321070829,
          "heightFactor": 0.08003453747347353,
          "deltaAngle": 0
        },
        "layer1": {
          "deltaX": -180.3231201171875,
          "deltaY": 0.79986572265625,
          "widthFactor": 1,
          "heightFactor": 1,
          "deltaAngle": 0
        }
      }
    },
    {
      "frameId": "f19",
      "title": "New frame",
      "titleLevel": 0,
      "notes": "",
      "timeoutMs": 0,
      "timeoutEnable": false,
      "transitionDurationMs": 1000,
      "showInFrameList": false,
      "showFrameNumber": false,
      "layerProperties": {
        "layer2": {
          "link": false,
          "referenceElementId": "rect42675",
          "outlineElementId": "rect7020",
          "transitionTimingFunction": "linear",
          "transitionRelativeZoom": 0,
          "transitionPathId": ""
        },
        "layer1": {
          "link": false,
          "referenceElementId": "rect7022",
          "outlineElementId": "rect7020",
          "transitionTimingFunction": "linear",
          "transitionRelativeZoom": 0,
          "transitionPathId": ""
        },
        "__sozi_auto__": {
          "link": false,
          "referenceElementId": "",
          "outlineElementId": "rect7020",
          "transitionTimingFunction": "linear",
          "transitionRelativeZoom": 0,
          "transitionPathId": ""
        }
      },
      "cameraStates": {
        "layer2": {
          "cx": 934.2190551757812,
          "cy": 607.0578002929688,
          "width": 160,
          "height": 90,
          "opacity": 1,
          "angle": 0,
          "clipped": false,
          "clipXOffset": 0,
          "clipYOffset": 0,
          "clipWidthFactor": 1,
          "clipHeightFactor": 1
        },
        "layer1": {
          "cx": 934.2190551757812,
          "cy": 607.0578002929688,
          "width": 160,
          "height": 90,
          "opacity": 1,
          "angle": 0,
          "clipped": false,
          "clipXOffset": 0,
          "clipYOffset": 0,
          "clipWidthFactor": 1,
          "clipHeightFactor": 1
        },
        "__sozi_auto__": {
          "cx": 934.2190551757812,
          "cy": 607.0578002929688,
          "width": 160,
          "height": 90,
          "opacity": 1,
          "angle": 0,
          "clipped": false,
          "clipXOffset": 0,
          "clipYOffset": 0,
          "clipWidthFactor": 1,
          "clipHeightFactor": 1
        }
      },
      "cameraOffsets": {
        "layer2": {
          "deltaX": 276.96368408203125,
          "deltaY": 166.5755615234375,
          "widthFactor": 0.09980239321070829,
          "heightFactor": 0.08003453747347353,
          "deltaAngle": 0
        },
        "layer1": {
          "deltaX": -187.82073974609375,
          "deltaY": -0.0968017578125,
          "widthFactor": 1,
          "heightFactor": 1,
          "deltaAngle": 0
        }
      }
    },
    {
      "frameId": "f20",
      "title": "New frame",
      "titleLevel": 0,
      "notes": "",
      "timeoutMs": 0,
      "timeoutEnable": false,
      "transitionDurationMs": 1000,
      "showInFrameList": false,
      "showFrameNumber": false,
      "layerProperties": {
        "layer2": {
          "link": false,
          "referenceElementId": "rect42675",
          "outlineElementId": "rect7022",
          "transitionTimingFunction": "linear",
          "transitionRelativeZoom": 0,
          "transitionPathId": ""
        },
        "layer1": {
          "link": false,
          "referenceElementId": "rect7024",
          "outlineElementId": "rect7022",
          "transitionTimingFunction": "linear",
          "transitionRelativeZoom": 0,
          "transitionPathId": ""
        },
        "__sozi_auto__": {
          "link": false,
          "referenceElementId": "",
          "outlineElementId": "rect7022",
          "transitionTimingFunction": "linear",
          "transitionRelativeZoom": 0,
          "transitionPathId": ""
        }
      },
      "cameraStates": {
        "layer2": {
          "cx": 1122.039794921875,
          "cy": 607.1546020507812,
          "width": 160,
          "height": 90,
          "opacity": 1,
          "angle": 0,
          "clipped": false,
          "clipXOffset": 0,
          "clipYOffset": 0,
          "clipWidthFactor": 1,
          "clipHeightFactor": 1
        },
        "layer1": {
          "cx": 1122.039794921875,
          "cy": 607.1546020507812,
          "width": 160,
          "height": 90,
          "opacity": 1,
          "angle": 0,
          "clipped": false,
          "clipXOffset": 0,
          "clipYOffset": 0,
          "clipWidthFactor": 1,
          "clipHeightFactor": 1
        },
        "__sozi_auto__": {
          "cx": 1122.039794921875,
          "cy": 607.1546020507812,
          "width": 160,
          "height": 90,
          "opacity": 1,
          "angle": 0,
          "clipped": false,
          "clipXOffset": 0,
          "clipYOffset": 0,
          "clipWidthFactor": 1,
          "clipHeightFactor": 1
        }
      },
      "cameraOffsets": {
        "layer2": {
          "deltaX": 464.784423828125,
          "deltaY": 166.67236328125,
          "widthFactor": 0.09980239321070829,
          "heightFactor": 0.08003453747347353,
          "deltaAngle": 0
        },
        "layer1": {
          "deltaX": -183.911376953125,
          "deltaY": -0.98309326171875,
          "widthFactor": 1,
          "heightFactor": 1,
          "deltaAngle": 0
        }
      }
    },
    {
      "frameId": "f21",
      "title": "New frame",
      "titleLevel": 0,
      "notes": "",
      "timeoutMs": 0,
      "timeoutEnable": false,
      "transitionDurationMs": 1000,
      "showInFrameList": false,
      "showFrameNumber": false,
      "layerProperties": {
        "layer2": {
          "link": false,
          "referenceElementId": "rect42675",
          "outlineElementId": "rect7024",
          "transitionTimingFunction": "linear",
          "transitionRelativeZoom": 0,
          "transitionPathId": ""
        },
        "layer1": {
          "link": false,
          "referenceElementId": "rect28902",
          "outlineElementId": "rect7024",
          "transitionTimingFunction": "linear",
          "transitionRelativeZoom": 0,
          "transitionPathId": ""
        },
        "__sozi_auto__": {
          "link": false,
          "referenceElementId": "",
          "outlineElementId": "rect7024",
          "transitionTimingFunction": "linear",
          "transitionRelativeZoom": 0,
          "transitionPathId": ""
        }
      },
      "cameraStates": {
        "layer2": {
          "cx": 1305.951171875,
          "cy": 608.1376953125,
          "width": 160,
          "height": 90,
          "opacity": 1,
          "angle": 0,
          "clipped": false,
          "clipXOffset": 0,
          "clipYOffset": 0,
          "clipWidthFactor": 1,
          "clipHeightFactor": 1
        },
        "layer1": {
          "cx": 1305.951171875,
          "cy": 608.1376953125,
          "width": 160,
          "height": 90,
          "opacity": 1,
          "angle": 0,
          "clipped": false,
          "clipXOffset": 0,
          "clipYOffset": 0,
          "clipWidthFactor": 1,
          "clipHeightFactor": 1
        },
        "__sozi_auto__": {
          "cx": 1305.951171875,
          "cy": 608.1376953125,
          "width": 160,
          "height": 90,
          "opacity": 1,
          "angle": 0,
          "clipped": false,
          "clipXOffset": 0,
          "clipYOffset": 0,
          "clipWidthFactor": 1,
          "clipHeightFactor": 1
        }
      },
      "cameraOffsets": {
        "layer2": {
          "deltaX": 648.69580078125,
          "deltaY": 167.65545654296875,
          "widthFactor": 0.09980239321070829,
          "heightFactor": 0.08003453747347353,
          "deltaAngle": 0
        },
        "layer1": {
          "deltaX": -0.592041015625,
          "deltaY": -125.2509765625,
          "widthFactor": 1,
          "heightFactor": 1,
          "deltaAngle": 0
        }
      }
    },
    {
      "frameId": "f22",
      "title": "New frame",
      "titleLevel": 0,
      "notes": "",
      "timeoutMs": 0,
      "timeoutEnable": false,
      "transitionDurationMs": 1000,
      "showInFrameList": false,
      "showFrameNumber": false,
      "layerProperties": {
        "layer2": {
          "link": false,
          "referenceElementId": "rect42675",
          "outlineElementId": "rect28902",
          "transitionTimingFunction": "linear",
          "transitionRelativeZoom": 0,
          "transitionPathId": ""
        },
        "layer1": {
          "link": false,
          "referenceElementId": "rect84771",
          "outlineElementId": "rect28902",
          "transitionTimingFunction": "linear",
          "transitionRelativeZoom": 0,
          "transitionPathId": ""
        },
        "__sozi_auto__": {
          "link": false,
          "referenceElementId": "",
          "outlineElementId": "rect28902",
          "transitionTimingFunction": "linear",
          "transitionRelativeZoom": 0,
          "transitionPathId": ""
        }
      },
      "cameraStates": {
        "layer2": {
          "cx": 1306.543212890625,
          "cy": 733.388671875,
          "width": 160,
          "height": 90,
          "opacity": 1,
          "angle": 0,
          "clipped": false,
          "clipXOffset": 0,
          "clipYOffset": 0,
          "clipWidthFactor": 1,
          "clipHeightFactor": 1
        },
        "layer1": {
          "cx": 1306.543212890625,
          "cy": 733.388671875,
          "width": 160,
          "height": 90,
          "opacity": 1,
          "angle": 0,
          "clipped": false,
          "clipXOffset": 0,
          "clipYOffset": 0,
          "clipWidthFactor": 1,
          "clipHeightFactor": 1
        },
        "__sozi_auto__": {
          "cx": 1306.543212890625,
          "cy": 733.388671875,
          "width": 160,
          "height": 90,
          "opacity": 1,
          "angle": 0,
          "clipped": false,
          "clipXOffset": 0,
          "clipYOffset": 0,
          "clipWidthFactor": 1,
          "clipHeightFactor": 1
        }
      },
      "cameraOffsets": {
        "layer2": {
          "deltaX": 649.287841796875,
          "deltaY": 292.90643310546875,
          "widthFactor": 0.09980239321070829,
          "heightFactor": 0.08003453747347353,
          "deltaAngle": 0
        },
        "layer1": {
          "deltaX": 182.7994384765625,
          "deltaY": -0.63836669921875,
          "widthFactor": 1.3333333333333333,
          "heightFactor": 1,
          "deltaAngle": 0
        }
      }
    },
    {
      "frameId": "f23",
      "title": "New frame",
      "titleLevel": 0,
      "notes": "",
      "timeoutMs": 0,
      "timeoutEnable": false,
      "transitionDurationMs": 1000,
      "showInFrameList": false,
      "showFrameNumber": false,
      "layerProperties": {
        "layer2": {
          "link": false,
          "referenceElementId": "rect42675",
          "outlineElementId": "rect28936",
          "transitionTimingFunction": "linear",
          "transitionRelativeZoom": 0,
          "transitionPathId": ""
        },
        "layer1": {
          "link": false,
          "referenceElementId": "rect28936",
          "outlineElementId": "rect28936",
          "transitionTimingFunction": "linear",
          "transitionRelativeZoom": 0,
          "transitionPathId": ""
        },
        "__sozi_auto__": {
          "link": false,
          "referenceElementId": "",
          "outlineElementId": "rect28936",
          "transitionTimingFunction": "linear",
          "transitionRelativeZoom": 0,
          "transitionPathId": ""
        }
      },
      "cameraStates": {
        "layer2": {
          "cx": 1123.7437744140625,
          "cy": 734.0270385742188,
          "width": 160,
          "height": 90,
          "opacity": 1,
          "angle": 0,
          "clipped": false,
          "clipXOffset": 0,
          "clipYOffset": 0,
          "clipWidthFactor": 1,
          "clipHeightFactor": 1
        },
        "layer1": {
          "cx": 1123.7437744140625,
          "cy": 734.0270385742188,
          "width": 160,
          "height": 90,
          "opacity": 1,
          "angle": 0,
          "clipped": false,
          "clipXOffset": 0,
          "clipYOffset": 0,
          "clipWidthFactor": 1,
          "clipHeightFactor": 1
        },
        "__sozi_auto__": {
          "cx": 1123.7437744140625,
          "cy": 734.0270385742188,
          "width": 160,
          "height": 90,
          "opacity": 1,
          "angle": 0,
          "clipped": false,
          "clipXOffset": 0,
          "clipYOffset": 0,
          "clipWidthFactor": 1,
          "clipHeightFactor": 1
        }
      },
      "cameraOffsets": {
        "layer2": {
          "deltaX": 466.4884033203125,
          "deltaY": 293.5447998046875,
          "widthFactor": 0.09980239321070829,
          "heightFactor": 0.08003453747347353,
          "deltaAngle": 0
        },
        "layer1": {
          "deltaX": 0,
          "deltaY": 0,
          "widthFactor": 1,
          "heightFactor": 1,
          "deltaAngle": 0
        }
      }
    },
    {
      "frameId": "f24",
      "title": "New frame",
      "titleLevel": 0,
      "notes": "",
      "timeoutMs": 0,
      "timeoutEnable": false,
      "transitionDurationMs": 1000,
      "showInFrameList": false,
      "showFrameNumber": false,
      "layerProperties": {
        "layer2": {
          "link": false,
          "referenceElementId": "rect42675",
          "outlineElementId": "rect66982",
          "transitionTimingFunction": "linear",
          "transitionRelativeZoom": 0,
          "transitionPathId": ""
        },
        "layer1": {
          "link": false,
          "referenceElementId": "rect66982",
          "outlineElementId": "rect66982",
          "transitionTimingFunction": "linear",
          "transitionRelativeZoom": 0,
          "transitionPathId": ""
        },
        "__sozi_auto__": {
          "link": false,
          "referenceElementId": "",
          "outlineElementId": "rect66982",
          "transitionTimingFunction": "linear",
          "transitionRelativeZoom": 0,
          "transitionPathId": ""
        }
      },
      "cameraStates": {
        "layer2": {
          "cx": 935.5841064453125,
          "cy": 735.2240600585938,
          "width": 160,
          "height": 90,
          "opacity": 1,
          "angle": 0,
          "clipped": false,
          "clipXOffset": 0,
          "clipYOffset": 0,
          "clipWidthFactor": 1,
          "clipHeightFactor": 1
        },
        "layer1": {
          "cx": 935.5841064453125,
          "cy": 735.2240600585938,
          "width": 160,
          "height": 90,
          "opacity": 1,
          "angle": 0,
          "clipped": false,
          "clipXOffset": 0,
          "clipYOffset": 0,
          "clipWidthFactor": 1,
          "clipHeightFactor": 1
        },
        "__sozi_auto__": {
          "cx": 935.5841064453125,
          "cy": 735.2240600585938,
          "width": 160,
          "height": 90,
          "opacity": 1,
          "angle": 0,
          "clipped": false,
          "clipXOffset": 0,
          "clipYOffset": 0,
          "clipWidthFactor": 1,
          "clipHeightFactor": 1
        }
      },
      "cameraOffsets": {
        "layer2": {
          "deltaX": 278.3287353515625,
          "deltaY": 294.7418212890625,
          "widthFactor": 0.09980239321070829,
          "heightFactor": 0.08003453747347353,
          "deltaAngle": 0
        },
        "layer1": {
          "deltaX": 0,
          "deltaY": 0,
          "widthFactor": 1,
          "heightFactor": 1,
          "deltaAngle": 0
        }
      }
    }
  ],
  "elementsToHide": [
    "rect4477",
    "rect863",
    "rect927",
    "rect16033",
    "rect927-3",
    "rect50909",
    "rect7150",
    "rect7704",
    "rect27155",
    "rect30600",
    "rect23701",
    "rect27153",
    "rect30874",
    "rect53782",
    "rect28674",
    "rect28900",
    "rect28704",
    "rect7020",
    "rect7022",
    "rect7024",
    "rect28902",
    "rect28936",
    "rect66982",
    "rect7729"
  ],
  "selectedFrames": [
    "f01"
  ],
  "selectedLayers": [
    "layer2",
    "layer1",
    "__sozi_auto__"
  ],
  "editableLayers": []
}